<?xml version='1.0' encoding='UTF-8'?>
<com.tikal.jenkins.plugins.multijob.MultiJobProject plugin="jenkins-multijob-plugin@1.23">
  <actions/>
  <description></description>
  <keepDependencies>false</keepDependencies>
  <properties>
    <hudson.plugins.buildblocker.BuildBlockerProperty plugin="build-blocker-plugin@1.7.3">
      <useBuildBlocker>false</useBuildBlocker>
      <blockLevel>GLOBAL</blockLevel>
      <scanQueueFor>DISABLED</scanQueueFor>
      <blockingJobs></blockingJobs>
    </hudson.plugins.buildblocker.BuildBlockerProperty>
    <hudson.model.ParametersDefinitionProperty>
      <parameterDefinitions>
        <hudson.model.TextParameterDefinition>
          <name>POD_NAME</name>
          <description></description>
          <defaultValue>mobile-aut2</defaultValue>
        </hudson.model.TextParameterDefinition>
      </parameterDefinitions>
    </hudson.model.ParametersDefinitionProperty>
  </properties>
  <scm class="hudson.scm.NullSCM"/>
  <canRoam>true</canRoam>
  <disabled>false</disabled>
  <blockBuildWhenDownstreamBuilding>false</blockBuildWhenDownstreamBuilding>
  <blockBuildWhenUpstreamBuilding>false</blockBuildWhenUpstreamBuilding>
  <triggers/>
  <concurrentBuild>false</concurrentBuild>
  <builders>
    <com.tikal.jenkins.plugins.multijob.MultiJobBuilder>
      <phaseName>create-pod</phaseName>
      <phaseJobs>
        <com.tikal.jenkins.plugins.multijob.PhaseJobsConfig>
          <jobName>create-pod-mobile-automation</jobName>
          <currParams>true</currParams>
          <exposedSCM>false</exposedSCM>
          <disableJob>false</disableJob>
          <parsingRulesPath></parsingRulesPath>
          <maxRetries>0</maxRetries>
          <enableRetryStrategy>false</enableRetryStrategy>
          <enableCondition>false</enableCondition>
          <abortAllJob>false</abortAllJob>
          <condition></condition>
          <configs class="empty-list"/>
          <killPhaseOnJobResultCondition>NEVER</killPhaseOnJobResultCondition>
          <buildOnlyIfSCMChanges>false</buildOnlyIfSCMChanges>
          <applyConditionOnlyIfNoSCMChanges>false</applyConditionOnlyIfNoSCMChanges>
        </com.tikal.jenkins.plugins.multijob.PhaseJobsConfig>
      </phaseJobs>
      <continuationCondition>ALWAYS</continuationCondition>
      <executionType>PARALLEL</executionType>
    </com.tikal.jenkins.plugins.multijob.MultiJobBuilder>
    <hudson.tasks.Shell>
      <command>sleep 1200s</command>
    </hudson.tasks.Shell>
    <com.tikal.jenkins.plugins.multijob.MultiJobBuilder>
      <phaseName>run smoke tests</phaseName>
      <phaseJobs>
        <com.tikal.jenkins.plugins.multijob.PhaseJobsConfig>
          <jobName>ios-smoke-tests</jobName>
          <currParams>true</currParams>
          <exposedSCM>false</exposedSCM>
          <disableJob>false</disableJob>
          <parsingRulesPath></parsingRulesPath>
          <maxRetries>0</maxRetries>
          <enableRetryStrategy>false</enableRetryStrategy>
          <enableCondition>false</enableCondition>
          <abortAllJob>false</abortAllJob>
          <condition></condition>
          <configs>
            <hudson.plugins.parameterizedtrigger.PredefinedBuildParameters plugin="parameterized-trigger@2.32">
              <properties>POD=warpdrive:${POD_NAME}-pod1
XPOD=warpdrive-xpod:${POD_NAME}-pod2
METAFILTER=smoke</properties>
            </hudson.plugins.parameterizedtrigger.PredefinedBuildParameters>
          </configs>
          <killPhaseOnJobResultCondition>NEVER</killPhaseOnJobResultCondition>
          <buildOnlyIfSCMChanges>false</buildOnlyIfSCMChanges>
          <applyConditionOnlyIfNoSCMChanges>false</applyConditionOnlyIfNoSCMChanges>
        </com.tikal.jenkins.plugins.multijob.PhaseJobsConfig>
      </phaseJobs>
      <continuationCondition>ALWAYS</continuationCondition>
      <executionType>PARALLEL</executionType>
    </com.tikal.jenkins.plugins.multijob.MultiJobBuilder>
  </builders>
  <publishers/>
  <buildWrappers/>
  <pollSubjobs>false</pollSubjobs>
</com.tikal.jenkins.plugins.multijob.MultiJobProject>